flasket/__init__.py
flasket/_utils.py
flasket/decorators.py
flasket/exceptions.py
flasket/flasket.py
flasket/logger.py
flasket/properties.py
flasket/templates.py
flasket/utils.py
flasket/api/openapi.yml
flasket/api/x-responses.yml
flasket/api/x-schemas.yml
flasket/backends/__init__.py
flasket/backends/_backend.py
flasket/backends/api.py
flasket/backends/dash.py
flasket/backends/static.py
flasket/clients/__init__.py
flasket/ext/__init__.py
flasket/ext/celery.py
flasket/middleware/__init__.py
flasket/middleware/gunicorn.py
flasket/testing/__init__.py
flasket-0.21.1.dist-info/LICENSE
flasket-0.21.1.dist-info/METADATA
flasket-0.21.1.dist-info/WHEEL
flasket-0.21.1.dist-info/entry_points.txt
flasket-0.21.1.dist-info/top_level.txt
flasket-0.21.1.dist-info/zip-safe
flasket-0.21.1.dist-info/RECORD
