Metadata-Version: 2.1
Name: flasket
Version: 0.21.1
Summary: (deprecated)
Author-email: Julien Lecomte <julien@lecomte.at>
License: MIT
Project-URL: Homepage, https://gitlab.com/jlecomte/python/flasket
Project-URL: Documentation, https://jlecomte.gitlab.io/python/flasket/
Project-URL: Source code, https://gitlab.com/jlecomte/python/flasket
Project-URL: Bug tracker, https://gitlab.com/jlecomte/python/flasket/-/issues
Classifier: License :: OSI Approved :: MIT License
Classifier: Intended Audience :: Developers
Classifier: Topic :: Internet :: WWW/HTTP :: HTTP Servers
Classifier: Topic :: Internet :: WWW/HTTP :: WSGI :: Application
Classifier: Topic :: Internet :: WWW/HTTP :: WSGI :: Server
Classifier: Framework :: Flask
Classifier: Development Status :: 3 - Alpha
Classifier: Programming Language :: Python :: 3 :: Only
Classifier: Programming Language :: Python :: 3.8
Classifier: Programming Language :: Python :: 3.9
Classifier: Programming Language :: Python :: 3.10
Classifier: Programming Language :: Python :: 3.11
Requires-Python: >=3.8
License-File: LICENSE
Requires-Dist: attr
Requires-Dist: gunicorn
Requires-Dist: flask-gordon
Requires-Dist: connexion[flask,swagger-ui] <3.0.0,>=2.14.2
Requires-Dist: flask <3.0.0
Requires-Dist: werkzeug <3.0.0
Requires-Dist: dash >=2.0.0
Requires-Dist: dash-bootstrap-components
Provides-Extra: celery
Requires-Dist: celery ; extra == 'celery'
Requires-Dist: redis ; extra == 'celery'
